{
    "belchertown_version": "1.3b1",
    "generated_timestamp": "12/22/2022 16:29:35",
    "colors": "#7cb5ec, #b2df8a, #f7a35c, #8c6bb1, #dd3497, #e4d354, #268bd2, #f45b5b, #6a3d9a, #33a02c",
    "chartgroup_title": "This Month",
    "tooltip_date_format": "dddd LL",
    "credits": "highcharts_default",
    "credits_url": "highcharts_default",
    "credits_position": "highcharts_default",
    "chart1": {
        "series": {
            "outTemp": {
                "obsType": "outTemp",
                "yAxis_label": "Max Temperature (\u00b0F)",
                "polar": "false",
                "zIndex": 1.0,
                "name": "Max Temperature",
                "color": "red",
                "rounding": 1.0,
                "data": [
                    [
                        1669206540000.0,
                        54.7
                    ],
                    [
                        1669292940000.0,
                        53.6
                    ],
                    [
                        1669379340000.0,
                        48.0
                    ],
                    [
                        1669465740000.0,
                        44.8
                    ],
                    [
                        1669552140000.0,
                        46.2
                    ],
                    [
                        1669638540000.0,
                        40.8
                    ],
                    [
                        1669724940000.0,
                        34.0
                    ],
                    [
                        1669811340000.0,
                        41.9
                    ],
                    [
                        1669897740000.0,
                        34.0
                    ],
                    [
                        1669984140000.0,
                        37.6
                    ],
                    [
                        1670070540000.0,
                        44.4
                    ],
                    [
                        1670156940000.0,
                        41.2
                    ],
                    [
                        1670243340000.0,
                        38.1
                    ],
                    [
                        1670329740000.0,
                        40.1
                    ],
                    [
                        1670416140000.0,
                        44.8
                    ],
                    [
                        1670502540000.0,
                        43.5
                    ],
                    [
                        1670588940000.0,
                        42.4
                    ],
                    [
                        1670675340000.0,
                        45.1
                    ],
                    [
                        1670761740000.0,
                        43.9
                    ],
                    [
                        1670848140000.0,
                        43.2
                    ],
                    [
                        1670934540000.0,
                        41.5
                    ],
                    [
                        1671020940000.0,
                        43.2
                    ],
                    [
                        1671107340000.0,
                        41.7
                    ],
                    [
                        1671193740000.0,
                        41.3
                    ],
                    [
                        1671280140000.0,
                        36.5
                    ],
                    [
                        1671366540000.0,
                        41.0
                    ],
                    [
                        1671452940000.0,
                        36.2
                    ],
                    [
                        1671539340000.0,
                        42.3
                    ],
                    [
                        1671625740000.0,
                        29.7
                    ],
                    [
                        1671712140000.0,
                        23.2
                    ]
                ]
            },
            "outTemp_min": {
                "obsType": "outTemp_min",
                "yAxis_label": "Min Temperature (\u00b0F)",
                "polar": "false",
                "name": "Min Temperature",
                "observation_type": "outTemp",
                "aggregate_type": "min",
                "color": "#7cb5ec",
                "rounding": 1.0,
                "data": [
                    [
                        1669206540000.0,
                        43.7
                    ],
                    [
                        1669292940000.0,
                        31.3
                    ],
                    [
                        1669379340000.0,
                        38.5
                    ],
                    [
                        1669465740000.0,
                        30.7
                    ],
                    [
                        1669552140000.0,
                        38.3
                    ],
                    [
                        1669638540000.0,
                        34.0
                    ],
                    [
                        1669724940000.0,
                        29.9
                    ],
                    [
                        1669811340000.0,
                        32.2
                    ],
                    [
                        1669897740000.0,
                        28.4
                    ],
                    [
                        1669984140000.0,
                        23.9
                    ],
                    [
                        1670070540000.0,
                        32.4
                    ],
                    [
                        1670156940000.0,
                        32.2
                    ],
                    [
                        1670243340000.0,
                        32.4
                    ],
                    [
                        1670329740000.0,
                        35.6
                    ],
                    [
                        1670416140000.0,
                        37.0
                    ],
                    [
                        1670502540000.0,
                        37.2
                    ],
                    [
                        1670588940000.0,
                        34.7
                    ],
                    [
                        1670675340000.0,
                        37.6
                    ],
                    [
                        1670761740000.0,
                        38.3
                    ],
                    [
                        1670848140000.0,
                        35.2
                    ],
                    [
                        1670934540000.0,
                        33.3
                    ],
                    [
                        1671020940000.0,
                        36.5
                    ],
                    [
                        1671107340000.0,
                        25.7
                    ],
                    [
                        1671193740000.0,
                        25.7
                    ],
                    [
                        1671280140000.0,
                        25.5
                    ],
                    [
                        1671366540000.0,
                        35.2
                    ],
                    [
                        1671452940000.0,
                        30.0
                    ],
                    [
                        1671539340000.0,
                        29.1
                    ],
                    [
                        1671625740000.0,
                        22.8
                    ],
                    [
                        1671712140000.0,
                        17.1
                    ]
                ]
            }
        },
        "options": {
            "renderTo": "chart1",
            "chart_group": "month",
            "title": "Temperature",
            "subtitle": "",
            "type": "spline",
            "gapsize": 86400000,
            "connectNulls": "false",
            "xAxis_categories": [],
            "plot_tooltip_date_format": "dddd LL",
            "css_width": "",
            "css_height": "",
            "legend": "true",
            "exporting": "false",
            "yAxis_label": "Min Temperature (\u00b0F)",
            "css_class": null
        }
    },
    "chart2": {
        "series": {
            "windDir": {
                "obsType": "windDir",
                "yAxis_label": "Wind Direction (\u00b0)",
                "polar": "false",
                "zIndex": 1.0,
                "yAxis": 1.0,
                "yAxis_max": 360.0,
                "lineWidth": 0.0,
                "aggregate_type": "avg",
                "marker": {
                    "enabled": "true"
                },
                "states": {
                    "hover": {
                        "lineWidthPlus": 0.0
                    }
                },
                "name": "Wind Direction",
                "yAxis_min": 0.0,
                "rounding": 0.0,
                "data": [
                    [
                        1669206540000.0,
                        181.0
                    ],
                    [
                        1669292940000.0,
                        186.0
                    ],
                    [
                        1669379340000.0,
                        172.0
                    ],
                    [
                        1669465740000.0,
                        178.0
                    ],
                    [
                        1669552140000.0,
                        181.0
                    ],
                    [
                        1669638540000.0,
                        185.0
                    ],
                    [
                        1669724940000.0,
                        178.0
                    ],
                    [
                        1669811340000.0,
                        179.0
                    ],
                    [
                        1669897740000.0,
                        173.0
                    ],
                    [
                        1669984140000.0,
                        176.0
                    ],
                    [
                        1670070540000.0,
                        169.0
                    ],
                    [
                        1670156940000.0,
                        165.0
                    ],
                    [
                        1670243340000.0,
                        187.0
                    ],
                    [
                        1670329740000.0,
                        187.0
                    ],
                    [
                        1670416140000.0,
                        183.0
                    ],
                    [
                        1670502540000.0,
                        179.0
                    ],
                    [
                        1670588940000.0,
                        179.0
                    ],
                    [
                        1670675340000.0,
                        174.0
                    ],
                    [
                        1670761740000.0,
                        177.0
                    ],
                    [
                        1670848140000.0,
                        180.0
                    ],
                    [
                        1670934540000.0,
                        190.0
                    ],
                    [
                        1671020940000.0,
                        176.0
                    ],
                    [
                        1671107340000.0,
                        189.0
                    ],
                    [
                        1671193740000.0,
                        186.0
                    ],
                    [
                        1671280140000.0,
                        182.0
                    ],
                    [
                        1671366540000.0,
                        183.0
                    ],
                    [
                        1671452940000.0,
                        180.0
                    ],
                    [
                        1671539340000.0,
                        178.0
                    ],
                    [
                        1671625740000.0,
                        176.0
                    ],
                    [
                        1671712140000.0,
                        165.0
                    ]
                ]
            },
            "windGust": {
                "obsType": "windGust",
                "yAxis_label": "Gust Speed (mph)",
                "polar": "false",
                "name": "Gust Speed",
                "yAxis_min": 0.0,
                "rounding": 0.0,
                "data": [
                    [
                        1669206540000.0,
                        8.0
                    ],
                    [
                        1669292940000.0,
                        3.0
                    ],
                    [
                        1669379340000.0,
                        11.0
                    ],
                    [
                        1669465740000.0,
                        6.0
                    ],
                    [
                        1669552140000.0,
                        15.0
                    ],
                    [
                        1669638540000.0,
                        13.0
                    ],
                    [
                        1669724940000.0,
                        6.0
                    ],
                    [
                        1669811340000.0,
                        9.0
                    ],
                    [
                        1669897740000.0,
                        4.0
                    ],
                    [
                        1669984140000.0,
                        2.0
                    ],
                    [
                        1670070540000.0,
                        7.0
                    ],
                    [
                        1670156940000.0,
                        11.0
                    ],
                    [
                        1670243340000.0,
                        2.0
                    ],
                    [
                        1670329740000.0,
                        2.0
                    ],
                    [
                        1670416140000.0,
                        4.0
                    ],
                    [
                        1670502540000.0,
                        4.0
                    ],
                    [
                        1670588940000.0,
                        6.0
                    ],
                    [
                        1670675340000.0,
                        7.0
                    ],
                    [
                        1670761740000.0,
                        7.0
                    ],
                    [
                        1670848140000.0,
                        3.0
                    ],
                    [
                        1670934540000.0,
                        3.0
                    ],
                    [
                        1671020940000.0,
                        7.0
                    ],
                    [
                        1671107340000.0,
                        3.0
                    ],
                    [
                        1671193740000.0,
                        3.0
                    ],
                    [
                        1671280140000.0,
                        4.0
                    ],
                    [
                        1671366540000.0,
                        15.0
                    ],
                    [
                        1671452940000.0,
                        6.0
                    ],
                    [
                        1671539340000.0,
                        13.0
                    ],
                    [
                        1671625740000.0,
                        9.0
                    ],
                    [
                        1671712140000.0,
                        13.0
                    ]
                ]
            },
            "windSpeed": {
                "obsType": "windSpeed",
                "yAxis_label": "Wind Speed (mph)",
                "polar": "false",
                "zIndex": 2.0,
                "name": "Wind Speed",
                "yAxis_min": 0.0,
                "rounding": 0.0,
                "data": [
                    [
                        1669206540000.0,
                        3.0
                    ],
                    [
                        1669292940000.0,
                        2.0
                    ],
                    [
                        1669379340000.0,
                        5.0
                    ],
                    [
                        1669465740000.0,
                        3.0
                    ],
                    [
                        1669552140000.0,
                        5.0
                    ],
                    [
                        1669638540000.0,
                        3.0
                    ],
                    [
                        1669724940000.0,
                        2.0
                    ],
                    [
                        1669811340000.0,
                        5.0
                    ],
                    [
                        1669897740000.0,
                        2.0
                    ],
                    [
                        1669984140000.0,
                        1.0
                    ],
                    [
                        1670070540000.0,
                        4.0
                    ],
                    [
                        1670156940000.0,
                        4.0
                    ],
                    [
                        1670243340000.0,
                        2.0
                    ],
                    [
                        1670329740000.0,
                        1.0
                    ],
                    [
                        1670416140000.0,
                        3.0
                    ],
                    [
                        1670502540000.0,
                        2.0
                    ],
                    [
                        1670588940000.0,
                        3.0
                    ],
                    [
                        1670675340000.0,
                        4.0
                    ],
                    [
                        1670761740000.0,
                        3.0
                    ],
                    [
                        1670848140000.0,
                        2.0
                    ],
                    [
                        1670934540000.0,
                        2.0
                    ],
                    [
                        1671020940000.0,
                        3.0
                    ],
                    [
                        1671107340000.0,
                        2.0
                    ],
                    [
                        1671193740000.0,
                        2.0
                    ],
                    [
                        1671280140000.0,
                        3.0
                    ],
                    [
                        1671366540000.0,
                        5.0
                    ],
                    [
                        1671452940000.0,
                        2.0
                    ],
                    [
                        1671539340000.0,
                        6.0
                    ],
                    [
                        1671625740000.0,
                        5.0
                    ],
                    [
                        1671712140000.0,
                        5.0
                    ]
                ]
            }
        },
        "options": {
            "renderTo": "chart2",
            "chart_group": "month",
            "title": "Wind Speed and Direction",
            "subtitle": "",
            "type": "spline",
            "gapsize": 86400000,
            "connectNulls": "false",
            "xAxis_categories": [],
            "plot_tooltip_date_format": "dddd LL",
            "css_width": "",
            "css_height": "",
            "legend": "true",
            "exporting": "false",
            "yAxis_label": "Wind Speed (mph)",
            "css_class": null
        }
    },
    "chart3": {
        "series": {
            "rainRate": {
                "obsType": "rainRate",
                "yAxis_label": "Rain Rate (in/hr)",
                "polar": "false",
                "yAxis": 1.0,
                "name": "Rain Rate",
                "rounding": 2.0,
                "data": [
                    [
                        1669206540000.0,
                        0.0
                    ],
                    [
                        1669292940000.0,
                        0.0
                    ],
                    [
                        1669379340000.0,
                        0.49
                    ],
                    [
                        1669465740000.0,
                        0.08
                    ],
                    [
                        1669552140000.0,
                        0.09
                    ],
                    [
                        1669638540000.0,
                        0.16
                    ],
                    [
                        1669724940000.0,
                        0.03
                    ],
                    [
                        1669811340000.0,
                        0.36
                    ],
                    [
                        1669897740000.0,
                        0.05
                    ],
                    [
                        1669984140000.0,
                        0.05
                    ],
                    [
                        1670070540000.0,
                        0.2
                    ],
                    [
                        1670156940000.0,
                        0.16
                    ],
                    [
                        1670243340000.0,
                        0.09
                    ],
                    [
                        1670329740000.0,
                        0.08
                    ],
                    [
                        1670416140000.0,
                        0.05
                    ],
                    [
                        1670502540000.0,
                        0.09
                    ],
                    [
                        1670588940000.0,
                        0.13
                    ],
                    [
                        1670675340000.0,
                        0.24
                    ],
                    [
                        1670761740000.0,
                        0.05
                    ],
                    [
                        1670848140000.0,
                        0.08
                    ],
                    [
                        1670934540000.0,
                        0.0
                    ],
                    [
                        1671020940000.0,
                        0.0
                    ],
                    [
                        1671107340000.0,
                        0.03
                    ],
                    [
                        1671193740000.0,
                        0.0
                    ],
                    [
                        1671280140000.0,
                        0.05
                    ],
                    [
                        1671366540000.0,
                        0.16
                    ],
                    [
                        1671452940000.0,
                        0.0
                    ],
                    [
                        1671539340000.0,
                        0.96
                    ],
                    [
                        1671625740000.0,
                        0.0
                    ],
                    [
                        1671712140000.0,
                        0.0
                    ]
                ]
            },
            "rainTotal": {
                "obsType": "rainTotal",
                "yAxis_label": "Rain Total (in)",
                "polar": "false",
                "name": "Rain Total",
                "rounding": 2.0,
                "data": [
                    [
                        1669206540000.0,
                        0.0
                    ],
                    [
                        1669292940000.0,
                        0.0
                    ],
                    [
                        1669379340000.0,
                        1.18
                    ],
                    [
                        1669465740000.0,
                        1.2
                    ],
                    [
                        1669552140000.0,
                        1.32
                    ],
                    [
                        1669638540000.0,
                        1.5
                    ],
                    [
                        1669724940000.0,
                        1.5
                    ],
                    [
                        1669811340000.0,
                        2.73
                    ],
                    [
                        1669897740000.0,
                        2.79
                    ],
                    [
                        1669984140000.0,
                        2.89
                    ],
                    [
                        1670070540000.0,
                        3.61
                    ],
                    [
                        1670156940000.0,
                        3.92
                    ],
                    [
                        1670243340000.0,
                        4.32
                    ],
                    [
                        1670329740000.0,
                        4.56
                    ],
                    [
                        1670416140000.0,
                        4.61
                    ],
                    [
                        1670502540000.0,
                        4.77
                    ],
                    [
                        1670588940000.0,
                        4.87
                    ],
                    [
                        1670675340000.0,
                        5.52
                    ],
                    [
                        1670761740000.0,
                        5.57
                    ],
                    [
                        1670848140000.0,
                        5.65
                    ],
                    [
                        1670934540000.0,
                        5.65
                    ],
                    [
                        1671020940000.0,
                        5.65
                    ],
                    [
                        1671107340000.0,
                        5.66
                    ],
                    [
                        1671193740000.0,
                        5.66
                    ],
                    [
                        1671280140000.0,
                        5.67
                    ],
                    [
                        1671366540000.0,
                        5.86
                    ],
                    [
                        1671452940000.0,
                        5.86
                    ],
                    [
                        1671539340000.0,
                        7.06
                    ],
                    [
                        1671625740000.0,
                        7.06
                    ],
                    [
                        1671712140000.0,
                        7.06
                    ]
                ]
            }
        },
        "options": {
            "renderTo": "chart3",
            "chart_group": "month",
            "title": "Rain",
            "subtitle": "",
            "type": "line",
            "gapsize": 86400000,
            "connectNulls": "false",
            "xAxis_categories": [],
            "plot_tooltip_date_format": "dddd LL",
            "css_width": "",
            "css_height": "",
            "legend": "true",
            "exporting": "false",
            "yAxis_label": "Rain Total (in)",
            "css_class": null
        }
    },
    "chart4": {
        "series": {
            "barometer": {
                "obsType": "barometer",
                "yAxis_label": "Barometer (mbar)",
                "polar": "false",
                "color": "#BECC00",
                "name": "Barometer",
                "rounding": 1.0,
                "data": [
                    [
                        1669206540000.0,
                        1024.6
                    ],
                    [
                        1669292940000.0,
                        1026.6
                    ],
                    [
                        1669379340000.0,
                        1022.8
                    ],
                    [
                        1669465740000.0,
                        1030.1
                    ],
                    [
                        1669552140000.0,
                        1017.5
                    ],
                    [
                        1669638540000.0,
                        1011.9
                    ],
                    [
                        1669724940000.0,
                        1015.4
                    ],
                    [
                        1669811340000.0,
                        999.9
                    ],
                    [
                        1669897740000.0,
                        1003.5
                    ],
                    [
                        1669984140000.0,
                        1016.1
                    ],
                    [
                        1670070540000.0,
                        1017.5
                    ],
                    [
                        1670156940000.0,
                        1016.4
                    ],
                    [
                        1670243340000.0,
                        1016.5
                    ],
                    [
                        1670329740000.0,
                        1019.4
                    ],
                    [
                        1670416140000.0,
                        1020.9
                    ],
                    [
                        1670502540000.0,
                        1015.1
                    ],
                    [
                        1670588940000.0,
                        1012.2
                    ],
                    [
                        1670675340000.0,
                        995.0
                    ],
                    [
                        1670761740000.0,
                        1003.5
                    ],
                    [
                        1670848140000.0,
                        1015.3
                    ],
                    [
                        1670934540000.0,
                        1022.8
                    ],
                    [
                        1671020940000.0,
                        1027.7
                    ],
                    [
                        1671107340000.0,
                        1032.9
                    ],
                    [
                        1671193740000.0,
                        1030.5
                    ],
                    [
                        1671280140000.0,
                        1021.3
                    ],
                    [
                        1671366540000.0,
                        1014.7
                    ],
                    [
                        1671452940000.0,
                        1022.0
                    ],
                    [
                        1671539340000.0,
                        1020.1
                    ],
                    [
                        1671625740000.0,
                        1028.2
                    ],
                    [
                        1671712140000.0,
                        1031.4
                    ]
                ]
            }
        },
        "options": {
            "renderTo": "chart4",
            "chart_group": "month",
            "title": "Barometer",
            "subtitle": "",
            "type": "spline",
            "gapsize": 86400000,
            "connectNulls": "false",
            "xAxis_categories": [],
            "plot_tooltip_date_format": "dddd LL",
            "css_width": "",
            "css_height": "",
            "legend": "true",
            "exporting": "false",
            "yAxis_label": "Barometer (mbar)",
            "css_class": null
        }
    }
}